clc99/__init__.py
clc99/clc99.py
clc99-2.3.dist-info/METADATA
clc99-2.3.dist-info/WHEEL
clc99-2.3.dist-info/top_level.txt
clc99-2.3.dist-info/RECORD
