Metadata-Version: 2.1
Name: clc99
Version: 2.3
Summary: This is a module to make your 'print' function looks like Metasploit.
Home-page: https://github.com/windows99-hue/clc99
Author: 99
Author-email: 3013907412@qq.com
Classifier: Programming Language :: Python :: 3
Classifier: License :: OSI Approved :: MIT License
Classifier: Operating System :: OS Independent
Requires-Python: >=3.6
Requires-Dist: colorama
